{
  "simulation_id": "sim_20251220_141517_0x08458f",
  "whale_address": "0x08458f7e9d2858027de579e4c3ca305475496b6f",
  "market_slug": "will-trump-visit-china-by-march-31",
  "is_elite": true,
  "confidence": 0.7500000000000002,
  "detection": {
    "timestamp": "2025-12-20T14:15:17",
    "market": "will-trump-visit-china-by-march-31",
    "price": 0.94,
    "size": 1.09
  },
  "results": [
    {
      "delay_seconds": 60,
      "delay_minutes": 1.0,
      "execution_time": "2025-12-20T14:16:17",
      "market_state_at_entry": {
        "price": 0.9499995249992875,
        "timestamp": "2025-12-20T14:16:37.705563",
        "source": "actual_lookup"
      },
      "simulated_entry_price": 0.9509495245242867,
      "slippage_percent": 0.1,
      "checked_at": "2025-12-20T14:16:37.705563",
      "pnl": null,
      "pnl_pct": null,
      "resolved": false
    },
    {
      "delay_seconds": 180,
      "delay_minutes": 3.0,
      "execution_time": "2025-12-20T14:18:17",
      "market_state_at_entry": {
        "price": 0.94,
        "timestamp": "2025-12-20T14:18:37.859569",
        "source": "actual_lookup"
      },
      "simulated_entry_price": 0.9409399999999999,
      "slippage_percent": 0.1,
      "checked_at": "2025-12-20T14:18:37.859569",
      "pnl": null,
      "pnl_pct": null,
      "resolved": false
    },
    {
      "delay_seconds": 300,
      "delay_minutes": 5.0,
      "execution_time": "2025-12-20T14:20:17",
      "market_state_at_entry": {
        "price": 0.9499995249992875,
        "timestamp": "2025-12-20T14:20:37.905639",
        "source": "actual_lookup"
      },
      "simulated_entry_price": 0.9509495245242867,
      "slippage_percent": 0.1,
      "checked_at": "2025-12-20T14:20:37.905639",
      "pnl": null,
      "pnl_pct": null,
      "resolved": false
    }
  ],
  "status": "completed",
  "created_at": "2025-12-20T14:15:36.703423",
  "delays_scheduled": [
    60,
    180,
    300
  ],
  "completed_at": "2025-12-20T14:20:37.920641"
}